{
  "id": "20250909_155607_CIBC_v11_0FH_-_Resume_Manthan_Patel_pdf",
  "filename": "20250909_155607_CIBC_v11.0FH_-_Resume_Manthan_Patel.pdf",
  "upload_date": "2025-09-09T15:56:07.663839",
  "parsed_data": {
    "raw_text": "MANTHAN\n \nPATEL\n \nM:\n \n+1\n \n(548)\n \n333-7145\n \n|\n \nmanthan.patel292000@gmail.com\n \n|\n \nHalifax,\n \nNS\n \n \nMotivated\n \nand\n \nclient-focused\n \nprofessional\n \nwith\n \n2+\n \nyears\n \nof\n \nexperience\n \nin\n \nfinancial\n \nconversations,\n \nconsultative\n \nsales,\n \nand\n \ngoal-based\n \nadvising.\n \nSkilled\n \nin\n \nbuilding\n \nstrong\n \nclient\n \nrelationships,\n \ndelivering\n \npersonalized\n \nservice,\n \nand\n \ndeepening\n \ntrust\n \nthrough\n \nproactive\n \nfinancial\n \nguidance.\n \nAdept\n \nat\n \nidentifying\n \nclient\n \npriorities\n \nand\n \nconnecting\n \nthem\n \nwith\n \ntailored\n \nsolutions\u2014ranging\n \nfrom\n \ninvestment\n \nand\n \ncredit\n \nsupport\n \nto\n \ndigital\n \nbanking\n \ntools.\n \nEager\n \nto\n \ncontribute\n \nas\n \nan\n \nAssociate\n \nFinancial\n \nAdvisor\n \nat\n \nCIBC\n \nby\n \nhelping\n \nindividuals\n \nand\n \nsmall\n \nbusiness\n \nclients\n \nachieve\n \ntheir\n \nlong-term\n \nfinancial\n \ngoals.\n \nCORE\n \nCOMPETENCIES\n \n \n \n\u25cf\n \nFinancial\n \nNeeds\n \nAssessment\n \n&\n \nPersonalized\n \nPlanning\n \n\u25cf\n \nCredit\n \n&\n \nInvestment\n \nSolution\n \nAwareness\n \n\u25cf\n \nClient\n \nOnboarding\n \n&\n \nRelationship\n \nBuilding\n \n\u25cf\n \nRetail\n \nBanking\n \n&\n \nBusiness\n \nBanking\n \nExposure\n \n\u25cf\n \nCommunity\n \nOutreach\n \n&\n \nBusiness\n \nDevelopment\n \n\u25cf\n \nReferral\n \n&\n \nNetworking\n \nStrategy\n \n\u25cf\n \nConflict\n \nResolution\n \n&\n \nClient\n \nRetention\n \n\u25cf\n \nCRM\n \n&\n \nBanking\n \nSystems:\n \nCDK,\n \nMicrosoft\n \n365,\n \nPOS\n \n\u25cf\n \nMobile\n \n&\n \nOnline\n \nBanking\n \nTools\n \nSupport\n \n\u25cf\n \nLLQP\n \n/\n \nCIRO-MFD\n \nLicense:\n \nEligible\n \n&\n \nopen\n \nto\n \ncomplete\n \n \nWORK\n \nEXPERIENCE\n \n \n \nKoepple\n \nCompanies(Five\n \nGuys),\n \nHalifax\n \n-\n \nShift\n \nManager\n \nMar\n \n2025\n \n-\n \nPresent\n \n\u25cf\n \nManaged\n \nstore\n \noperations\n \nand\n \nled\n \na\n \n10+\n \nperson\n \nteam\n \nto\n \nensure\n \nhigh-quality\n \nservice\n \ndelivery.\n \n\u25cf\n \nResolved\n \nclient\n \nconcerns\n \nprofessionally\n \nand\n \nensured\n \npositive\n \ncustomer\n \nexperiences.\n \n\u25cf\n \nDeveloped\n \nteam\n \ntrust,\n \nresulting\n \nin\n \nhigher\n \nretention\n \nand\n \nimproved\n \ncustomer\n \nservice\n \nmetrics.\n \n\u25cf\n \nSupported\n \ndaily\n \noperations:\n \ncash\n \nhandling,\n \nstaffing\n \nschedules,\n \nand\n \nworkflow\n \nefficiency\n \n(12%).\n \n \nSterling\n \nHonda,\n \nHamilton\n \n-\n \nService\n \nAdvisor\n \nMay\n \n2024\n \n-\n \nJun\n \n2025\n \n\u25cf\n \nAssisted\n \n20+\n \nclients\n \ndaily\n \nwith\n \nvehicle\n \nservice\n \nplans,\n \nexplaining\n \ncosts\n \nand\n \nrecommending\n \nservice\n \npackages\n \nthat\n \nmet\n \nindividual\n \nneeds.\n \n\u25cf\n \nAchieved\n \n22%\n \nincrease\n \nin\n \nmaintenance\n \npackage\n \nsales\n \nthrough\n \ngoal-based\n \nconversations.\n \n\u25cf\n \nCoordinated\n \nwith\n \ntechnical\n \nstaff\n \nto\n \nensure\n \non-time\n \ndelivery\n \nand\n \nfollow-through,\n \nenhancing\n \nclient\n \ntrust.\n \n\u25cf\n \nInitiated\n \nreferral-driven\n \nprograms\n \nand\n \nsupported\n \nfollow-up\n \nappointments\n \nto\n \nretain\n \nlong-term\n \ncustomers.\n \n \n \nB\n \nTown\n \nAutos\n \nTricity,\n \nKitchener\n \n-\n \nSales\n \nConsultant(Part-time)\n \nMay\n \n2023\n \n-\n \nApr\n \n2024\n \n\u25cf\n \nWorked\n \nas\n \na\n \ntrusted\n \nadvisor\n \nto\n \nclients\n \nby\n \nassessing\n \nlifestyle\n \nand\n \nbudget\n \nto\n \nrecommend\n \nfinancing\n \nand\n \nvehicle\n \nsolutions.\n \n\u25cf\n \nConsistently\n \nexceeded\n \nmonthly\n \ntargets\n \n(7\u201310\n \nsales/month)\n \nthrough\n \npersonalized\n \nservice\n \nand\n \nrelationship\n \nnurturing.\n \n\u25cf\n \nFacilitated\n \nvehicle\n \nfinancing\n \ndiscussions,\n \nexplaining\n \nrepayment\n \nterms,\n \ndown\n \npayments,\n \nand\n \noptions\u2014building\n \nfinancial\n \nliteracy\n \namong\n \nclients.\n \n\u25cf\n \nLeveraged\n \nnetworking\n \nand\n \nreferrals\n \nto\n \ndrive\n \nconsistent\n \nlead\n \ngeneration.\n \n \n \nEDUCATION\n \n \n \n \nPostgraduate\n \nin\n \nWeb\n \nDevelopment,\n \nConestoga\n \nCollege,\n \nKitchener,\n \nON,\n \nGPA:3.8/4.0\n \nAug\n \n2024\n \n \nBachelors\n \nof\n \nComputer\n \nEngineering,\n \nGujarat\n \nTechnological\n \nUniversity,\n \nIndia,\n \nGPA:3.73/4.0\n \nJun\n \n2021\n \n \n \nLEADERSHIP\n \nSKILLS\n \n&\n \nAWARDS\n \n \n \n\u25cf\n \n\u201cShift\n \nStar\n \nof\n \nthe\n \nMonth\u201d\n \n\u2013\n \nFive\n \nGuys\n \n(Team\n \nLeadership\n \n&\n \nCustomer\n \nSatisfaction)\n \n\u25cf\n \nYouth\n \nParliament\n \nof\n \nIndia\n \nDelegate\n \n(2018)\n \n\u2013\n \nRepresented\n \ncollege\n \nnationally\n \n\u25cf\n \nStudent\n \nLeader\n \n\u2013\n \nCSI\n \n&\n \nGDSC\n \nWaterloo\n \nEvents\n \n(Event\n \nplanning\n \n&\n \ntechnical\n \nteam\n \nlead)\n \n \nCAREER\n \nINTERESTS\n \n \n\u25cf\n \nPersonal\n \nfinance,\n \nbanking\n \ninnovation,\n \nrelationship\n \nadvising,\n \nleadership\n \ndevelopment\n \n\u25cf\n \nCommitted\n \nto\n \nSun\n \nLife\u2019s\n \nTraining\n \n&\n \nDevelopment\n \nPath\n \n",
    "contact_info": {
      "email": "manthan.patel292000@gmail.com",
      "phone": null,
      "linkedin": null,
      "name": "MANTHAN"
    },
    "skills": {
      "all_skills": [
        "rust",
        "go"
      ],
      "categorized": {
        "programming": [
          "rust",
          "go"
        ]
      },
      "skill_count": 2
    },
    "experience": {
      "estimated_years": 0,
      "years_mentioned": [
        "20",
        "20",
        "20",
        "20",
        "20",
        "20",
        "20",
        "20",
        "20"
      ],
      "potential_titles": [
        "leadership",
        "Manager",
        "lead",
        "Leader",
        "LEADERSHIP",
        "Engineering",
        "Leadership",
        "Consultant"
      ],
      "title_count": 8
    },
    "education": {
      "degrees": [
        "Postgraduate",
        "Associate"
      ],
      "education_mentioned": true,
      "degree_count": 2
    },
    "keywords": {
      "top_keywords": [
        [
          "client",
          10
        ],
        [
          "servic",
          7
        ],
        [
          "financi",
          6
        ],
        [
          "bank",
          6
        ],
        [
          "person",
          5
        ],
        [
          "develop",
          5
        ],
        [
          "relationship",
          4
        ],
        [
          "trust",
          4
        ],
        [
          "support",
          4
        ],
        [
          "team",
          4
        ],
        [
          "custom",
          4
        ],
        [
          "experi",
          3
        ],
        [
          "sale",
          3
        ],
        [
          "advisor",
          3
        ],
        [
          "busi",
          3
        ],
        [
          "plan",
          3
        ],
        [
          "ensur",
          3
        ],
        [
          "vehicl",
          3
        ],
        [
          "financ",
          3
        ],
        [
          "leadership",
          3
        ]
      ],
      "total_words": 296,
      "unique_words": 192
    },
    "summary_stats": {
      "character_count": 4177,
      "word_count": 445,
      "line_count": 912,
      "avg_words_per_line": 0.48793859649122806
    }
  }
}