{
  "id": "20250909_153843_Copy_of_v11_0FH_-_Resume_Manthan_Patel_3_pdf",
  "filename": "20250909_153843_Copy_of_v11.0FH_-_Resume_Manthan_Patel_3.pdf",
  "upload_date": "2025-09-09T15:38:43.726600",
  "parsed_data": {
    "raw_text": "MANTHAN\n \nPATEL\n \nM:\n \n+1\n \n(548)\n \n333-7145\n \n|\n \nmanthan.patel292000@gmail.com\n \n|\n \nHalifax,\n \nNS\n \n \nClient-centric\n \nand\n \nresults-driven\n \nprofessional\n \nwith\n \n2+\n \nyears\n \nof\n \nsuccess\n \nin\n \ncustomer\n \nservice,\n \nfinancial\n \nconversations,\n \nand\n \nconsultative\n \nsales\n \nacross\n \nretail\n \nand\n \nautomotive\n \nindustries.\n \nExperienced\n \nin\n \nbuilding\n \nlong-term\n \nrelationships,\n \ndeveloping\n \npersonalized\n \nsolutions,\n \nand\n \nguiding\n \nclients\n \ntoward\n \ninformed\n \nfinancial\n \ndecisions.\n \nKnown\n \nfor\n \nreliability ,\n \nindependence,\n \nand\n \na\n \nstrong\n \ndesire\n \nto\n \nhelp\n \nothers\n \nsucceed\n \nfinancially .\n \nEager\n \nto\n \ngrow\n \nas\n \na\n \nFinancial\n \nAdvisor\n \nby\n \ncontributing\n \nto\n \nSun\n \nLife\u2019 s\n \nmission\n \nof\n \nmaking\n \ncommunities\n \nfinancially\n \nstronger .\n \nCORE\n \nCOMPETENCIES\n \n \n \n\u25cf\n \nFinancial\n \nPlanning\n \nBasics\n \n&\n \nRoadmapping\n \n\u25cf\n \nInsurance\n \n&\n \nInvestment\n \nProduct\n \nAwareness\n \n\u25cf\n \nGoal-Based\n \nClient\n \nAdvising\n \n\u25cf\n \nClient\n \nProspecting\n \n&\n \nNeeds\n \nAnalysis\n \n\u25cf\n \nSales\n \n&\n \nRelationship\n \nDevelopment\n \n\u25cf\n \nConflict\n \nResolution\n \n&\n \nCustomer\n \nRetention\n \n\u25cf\n \nTeam\n \nLeadership\n \n&\n \nStaff\n \nMentoring\n \n\u25cf\n \nCRM\n \nTools:\n \nCDK\n \nDrive,\n \nMicrosoft\n \n365,\n \nPOS\n \n\u25cf\n \nLLQP\n \n/\n \nMutual\n \nFund\n \nLicense\n \n(open\n \nto\n \nlearn)\n \n \nWORK\n \nEXPERIENCE\n \n \n \nKoepple\n \nCompanies(Five\n \nGuys),\n \nHalifax\n \n-\n \nShift\n \nManager\n \nMar\n \n2025\n \n-\n \nPresent\n \n\u25cf\n \nTrained\n \nand\n \nonboarded\n \n10+\n \nnew\n \nhires\n \non\n \nFive\n \nGuys'\n \nfood\n \npreparation\n \nand\n \ncustomer\n \nservice\n \nprotocols,\n \nensuring\n \nconsistent\n \nquality\n \nand\n \nservice\n \nstandards\n \nacross\n \nall\n \nshifts\n \nmanaged.\n \n\u25cf\n \nManaged\n \ndaily\n \noperations\n \nincluding\n \nstaffing,\n \ninventory,\n \ncash\n \nflow,\n \nand\n \ncustomer\n \nsatisfaction\n \nmetrics.\n \n\u25cf\n \nResolved\n \nclient\n \nconcerns\n \nefficiently,\n \nensuring\n \nlong-term\n \nloyalty\n \nand\n \nreferrals.\n \n\u25cf\n \nMaintained\n \nteam\n \nmorale\n \nand\n \ntrust\n \nwhile\n \nimproving\n \nspeed\n \nand\n \nquality\n \nof\n \nservice\n \nby\n \n12%.\n \n \nSterling\n \nHonda,\n \nHamilton\n \n-\n \nService\n \nAdvisor\n \nMay\n \n2024\n \n-\n \nJun\n \n2025\n \n\u25cf\n \nAssisted\n \n20+\n \nclients\n \ndaily\n \nwith\n \nvehicle\n \nservice\n \nplans\u2014explaining\n \ncosts\n \nand\n \nrecommending\n \nservice\n \npackages\n \nthat\n \nmet\n \nindividual\n \nneeds.\n \n\u25cf\n \nAchieved\n \n22%\n \nincrease\n \nin\n \nmaintenance\n \npackage\n \nsales\n \nthrough\n \ngoal-based\n \nconversations.\n \n\u25cf\n \nCoordinated\n \nwith\n \ntechnical\n \nstaff\n \nto\n \nensure\n \non-time\n \ndelivery\n \nand\n \nfollow-through,\n \nenhancing\n \nclient\n \ntrust.\n \n\u25cf\n \nInitiated\n \nreferral-driven\n \nprograms\n \nand\n \nsupported\n \nfollow-up\n \nappointments\n \nto\n \nretain\n \nlong-term\n \ncustomers.\n \n \n \nB\n \nTown\n \nAutos\n \nTricity,\n \nKitchener\n \n-\n \nSales\n \nConsultant(Part-time)\n \nMay\n \n2023\n \n-\n \nApr\n \n2024\n \n\u25cf\n \nWorked\n \nas\n \na\n \ntrusted\n \nadvisor\n \nto\n \nclients\n \nby\n \nassessing\n \nlifestyle\n \nand\n \nbudget\n \nto\n \nrecommend\n \nfinancing\n \nand\n \nvehicle\n \nsolutions.\n \n\u25cf\n \nConsistently\n \nexceeded\n \nmonthly\n \ntargets\n \n(7\u201310\n \nsales/month)\n \nthrough\n \npersonalized\n \nservice\n \nand\n \nrelationship\n \nnurturing.\n \n\u25cf\n \nFacilitated\n \nvehicle\n \nfinancing\n \ndiscussions,\n \nexplaining\n \nrepayment\n \nterms,\n \ndown\n \npayments,\n \nand\n \noptions\u2014building\n \nfinancial\n \nliteracy\n \namong\n \nclients.\n \n\u25cf\n \nLeveraged\n \nnetworking\n \nand\n \nreferrals\n \nto\n \ndrive\n \nconsistent\n \nlead\n \ngeneration.\n \n \n \nEDUCATION\n \n \n \n \nPostgraduate\n \nin\n \nWeb\n \nDevelopment,\n \nConestoga\n \nCollege,\n \nKitchener,\n \nON,\n \nGPA:3.8/4.0\n \nAug\n \n2024\n \n \nBachelors\n \nof\n \nComputer\n \nEngineering,\n \nGujarat\n \nTechnological\n \nUniversity,\n \nIndia,\n \nGPA:3.73/4.0\n \nJun\n \n2021\n \n \n \nLEADERSHIP\n \nSKILLS\n \n&\n \nAWARDS\n \n \n \n\u25cf\n \n\u201cShift\n \nStar\n \nof\n \nthe\n \nMonth\u201d\n \n\u2013\n \nFive\n \nGuys\n \n(Team\n \nLeadership\n \n&\n \nCustomer\n \nSatisfaction)\n \n\u25cf\n \nYouth\n \nParliament\n \nof\n \nIndia\n \nDelegate\n \n(2018)\n \n\u2013\n \nRepresented\n \ncollege\n \nnationally\n \n\u25cf\n \nStudent\n \nLeader\n \n\u2013\n \nCSI\n \n&\n \nGDSC\n \nWaterloo\n \nEvents\n \n(Event\n \nplanning\n \n&\n \ntechnical\n \nteam\n \nlead)\n \n \nINTERESTS\n \n \n\u25cf\n \nPersonal\n \nfinance,\n \nleadership\n \ndevelopment,\n \nclient\n \nadvisory,\n \ncontinuous\n \nlearning,\n \nfinancial\n \nliteracy\n \nadvocacy\n \n\u25cf\n \nCommitted\n \nto\n \nSun\n \nLife\u2019s\n \nTraining\n \n&\n \nDevelopment\n \nPath\n \n",
    "contact_info": {
      "email": "manthan.patel292000@gmail.com",
      "phone": null,
      "linkedin": null,
      "name": "MANTHAN"
    },
    "skills": {
      "all_skills": [
        "go",
        "rust"
      ],
      "categorized": {
        "programming": [
          "go",
          "rust"
        ]
      },
      "skill_count": 2
    },
    "experience": {
      "estimated_years": 0,
      "years_mentioned": [
        "20",
        "20",
        "20",
        "20",
        "20",
        "20",
        "20",
        "20",
        "20"
      ],
      "potential_titles": [
        "LEADERSHIP",
        "Leadership",
        "Consultant",
        "lead",
        "Manager",
        "leadership",
        "Engineering",
        "Leader"
      ],
      "title_count": 8
    },
    "education": {
      "degrees": [
        "Postgraduate"
      ],
      "education_mentioned": true,
      "degree_count": 1
    },
    "keywords": {
      "top_keywords": [
        [
          "client",
          9
        ],
        [
          "servic",
          8
        ],
        [
          "financi",
          8
        ],
        [
          "custom",
          6
        ],
        [
          "develop",
          5
        ],
        [
          "sale",
          4
        ],
        [
          "team",
          4
        ],
        [
          "leadership",
          4
        ],
        [
          "relationship",
          3
        ],
        [
          "person",
          3
        ],
        [
          "advisor",
          3
        ],
        [
          "five",
          3
        ],
        [
          "shift",
          3
        ],
        [
          "manag",
          3
        ],
        [
          "ensur",
          3
        ],
        [
          "consist",
          3
        ],
        [
          "trust",
          3
        ],
        [
          "vehicl",
          3
        ],
        [
          "financ",
          3
        ],
        [
          "halifax",
          2
        ]
      ],
      "total_words": 294,
      "unique_words": 202
    },
    "summary_stats": {
      "character_count": 4127,
      "word_count": 444,
      "line_count": 902,
      "avg_words_per_line": 0.49223946784922396
    }
  }
}